talon/__init__.py
talon/environment.py
talon/errors.py
talon/nodes.py
talon/symbols.py
talon/syntax.lark
talon/talon.py
talon/transformer.py
talonlang-1.2.0.dist-info/LICENSE
talonlang-1.2.0.dist-info/METADATA
talonlang-1.2.0.dist-info/WHEEL
talonlang-1.2.0.dist-info/entry_points.txt
talonlang-1.2.0.dist-info/top_level.txt
talonlang-1.2.0.dist-info/RECORD
