Metadata-Version: 2.1
Name: talonlang
Version: 1.2.0
Summary: The Talon programming language
Home-page: https://github.com/MystPi/talon
Author: MystPi
License: MIT
Platform: UNKNOWN
Classifier: License :: OSI Approved :: MIT License
Classifier: Programming Language :: Python :: 3
License-File: LICENSE
Requires-Dist: lark
Requires-Dist: tinted
